{
  "sweets": [
      {
          "id": 1,
          "img": "./Images/Category/Sweets/Trilece_Caramel2.jpg",
          "bg": "fcf1ed",
          "title": "Trilece Caramel",
          "desc": "A Turkish sweet cake covered by caramel",
          "price": 15
      },
      {
          "id": 2,
          "img": "./Images/Category/Sweets/Trilece_Strawberry.jpg",
          "bg": "fcf1ed",
          "title": "Trilece Strawberry",
          "desc": "A Turkish sweet cake covered by strawberry gel layer",
          "price": 15
      },
      {
          "id": 3,
          "img": "./Images/Category/Sweets/Trilece_Pistachio.jpg",
          "bg": "fcf1ed",
          "title": "Trilece Pistachio",
          "desc": "A Turkish sweet cake covered by pistachio",
          "price": 15
      },
      {
          "id": 4,
          "img": "./Images/Category/Sweets/Lutos.jpg",
          "bg": "fcf1ed",
          "title": "Lutos",
          "desc": "Lutos cake",
          "price": 12
      },
      {
          "id": 5,
          "img": "./Images/Category/Sweets/Lebanese_Nights_Dessert.jpg",
          "bg": "fcf1ed",
          "title": "Lebanese Nights Dessert",
          "desc": "Made from a silky semolina based pudding, topped with Ashta (thick cream), whipping cream and pistachios",
          "price": 15
      },
      {
          "id": 6,
          "img": "./Images/Category/Sweets/Kinder_Bueno.jpg",
          "bg": "fcf1ed",
          "title": "Kinder Bueno",
          "desc": "Kinder Bueno cake",
          "price": 12
      },
      {
          "id": 7,
          "img": "./Images/Category/Sweets/Tiramisu.jpg",
          "bg": "fcf1ed",
          "title": "Tiramisu",
          "desc": "A coffee-flavoured Italian dessert. It is made of ladyfingers dipped in coffee, layered with a whipped mixture of eggs, sugar, and mascarpone cheese, flavoured with cocoa",
          "price": 12
      },
      {
          "id": 8,
          "img": "./Images/Category/Sweets/Khashkhash.jpg",
          "bg": "fcf1ed",
          "title": "Khash-khash",
          "desc": "Layered crackers with cream and toasted vermicelli",
          "price": 15
      },
      {
          "id": 9,
          "img": "./Images/Category/Sweets/Alfajores.jpg",
          "bg": "fcf1ed",
          "title": "Alfajores",
          "desc": "It's a sandwich made of two discs of dough with a filling in between",
          "price": 35
      },
      {
          "id": 10,
          "img": "./Images/Category/Sweets/Macaron.jpg",
          "bg": "fcf1ed",
          "title": "Macaron",
          "desc": "Sweet meringue-based confection made with egg white, icing sugar, granulated sugar, almond meal, and food colouring.",
          "price": 35
      },
      {
          "id": 11,
          "img": "./Images/Category/Sweets/Betefour.jpg",
          "bg": "fcf1ed",
          "title": "Betefour",
          "desc": "Egyptian butter cookies",
          "price": 40
      },
      {
          "id": 12,
          "img": "./Images/Category/Sweets/Contessa.jpg",
          "bg": "fcf1ed",
          "title": "Contessa",
          "desc": "Addictive Arabian cuisine",
          "price": 35
      },
      {
          "id": 13,
          "img": "./Images/Category/Sweets/English_Cake.jpg",
          "bg": "fcf1ed",
          "title": "English Cake",
          "desc": "The famous English Cake",
          "price": 35
      },
      {
          "id": 14,
          "img": "./Images/Category/Sweets/Dates_Cake.jpg",
          "bg": "fcf1ed",
          "title": "Dates Cake / Ma'amoul",
          "desc": "Flour or semolina cakes filled with dates",
          "price": 90
      },
      {
          "id": 15,
          "img": "./Images/Category/Sweets/Ghraybeh.jpg",
          "bg": "fcf1ed",
          "title": "Ghraybeh",
          "desc": "Delicious and delicate Middle Eastern cookies that melt in your mouth",
          "price": 40
      },
      {
          "id": 16,
          "img": "./Images/Category/Sweets/Cups.jpg",
          "bg": "fcf1ed",
          "title": "Sweet Cups",
          "desc": "Various sweet cups with different tasties",
          "price": 4
      },
      {
          "id": 17,
          "img": "./Images/Category/Sweets/Strawberry_Cake.jpg",
          "bg": "fcf1ed",
          "title": "Strawberry Cake",
          "desc": "Fresh strawberries, this strawberry cake is one of the simplest, most delicious cakes",
          "price": 120
      },
      {
          "id": 18,
          "img": "./Images/Category/Sweets/Ferrero_Rocher_Cake.jpg",
          "bg": "fcf1ed",
          "title": "Ferrero Rocher Cake",
          "desc": "This Ferrero Rocher Cake is your favorite chocolate hazelnut treat in cake form! Chocolate hazelnut cake layers and with a Nutella buttercream",
          "price": 100
      },
      {
          "id": 19,
          "img": "./Images/Category/Sweets/Nutella_Cake.jpg",
          "bg": "fcf1ed",
          "title": "Nutella Cake",
          "desc": "This Nutella Cake recipe is every Nutella lover’s dream cake! It’s a moist chocolate cake with a rich chocolate Nutella buttercream frosting smothered between each layer",
          "price": 100
      },
      {
          "id": 20,
          "img": "./Images/Category/Sweets/Oreo_Cake.jpg",
          "bg": "fcf1ed",
          "title": "Oreo Cake",
          "desc": "Impressive chocolate cake which layered and topped with Oreo whipped cream",
          "price": 100
      }
  ],
  "pastries": [
      {
          "id": 51,
          "img": "./Images/Category/Pastries/Beef_Meat.jpg",
          "bg": "f5fbfd",
          "title": "Beef Meat",
          "desc": "Pastry filled with Beef Meat",
          "price": 40
      },
      {
          "id": 52,
          "img": "./Images/Category/Pastries/Chicken.jpg",
          "bg": "f5fbfd",
          "title": "Chicken",
          "desc": "Pastry filled with Chicken",
          "price": 35
      },
      {
          "id": 53,
          "img": "./Images/Category/Pastries/Potato.jpg",
          "bg": "f5fbfd",
          "title": "Potato",
          "desc": "Pastry filled with Potato",
          "price": 35
      },
      {
          "id": 54,
          "img": "./Images/Category/Pastries/Potato_Discs.jpg",
          "bg": "f5fbfd",
          "title": "Potato Discs",
          "desc": "Potato discs covered by bread crumbs",
          "price": 35
      },
      {
          "id": 55,
          "img": "./Images/Category/Pastries/Sausage.jpg",
          "bg": "f5fbfd",
          "title": "Sausage",
          "desc": "Pastry filled with Sausage",
          "price": 35
      },
      {
          "id": 56,
          "img": "./Images/Category/Pastries/Tuna.jpg",
          "bg": "f5fbfd",
          "title": "Tuna",
          "desc": "Pastry filled with Tuna",
          "price": 35
      },
      {
          "id": 57,
          "img": "./Images/Category/Pastries/Pizza1.jpg",
          "bg": "f5fbfd",
          "title": "Pizza",
          "desc": "Pizza Pastry",
          "price": 35
      },
      {
          "id": 58,
          "img": "./Images/Category/Pastries/Pizza2.jpg",
          "bg": "f5fbfd",
          "title": "Pizza Filling",
          "desc": "Pastry filled with Pizza mix",
          "price": 35
      },
      {
          "id": 59,
          "img": "./Images/Category/Pastries/Olives.jpg",
          "bg": "f5fbfd",
          "title": "Olives",
          "desc": "Pastry filled with Olives",
          "price": 35
      },
      {
          "id": 60,
          "img": "./Images/Category/Pastries/Mozzarella_Sticks.jpg",
          "bg": "f5fbfd",
          "title": "Mozzarella Sticks",
          "desc": "Mozzarella cheese covered by bread crumbs",
          "price": 35
      },
      {
          "id": 61,
          "img": "./Images/Category/Pastries/Fatayer.jpg",
          "bg": "f5fbfd",
          "title": "Fatayer",
          "desc": "Fatayer filled with Spinach or Zaatar",
          "price": 65
      },
      {
          "id": 62,
          "img": "./Images/Category/Pastries/Kibbeh.jpg",
          "bg": "f5fbfd",
          "title": "Kibbeh",
          "desc": "Kibbeh is a family of dishes based on spiced ground meat, onions, and grain, popular in Middle Eastern cuisine. In Levantine cuisine, kibbeh is usually made by pounding bulgur wheat together with meat into a fine paste and forming it into balls with toasted pine nuts and spices",
          "price": 4
      }
  ],
  "ourCuisine": [
      {
          "id": 71,
          "img": "./Images/Category/OurCuisine/Cabbage_Roll.jpg",
          "bg": "fbf0f4",
          "title": "Cabbage Roll",
          "desc": "Filled with rice & Beaf or Lamb meat",
          "price": 50
      },
      {
          "id": 72,
          "img": "./Images/Category/OurCuisine/Grape_leaves.jpg",
          "bg": "fbf0f4",
          "title": "Grape leaves",
          "desc": "Filled with rcse & Beaf or Lamb meat",
          "price": 50
      },
      {
          "id": 73,
          "img": "./Images/Category/OurCuisine/Maftool.jpg",
          "bg": "fbf0f4",
          "title": "Maftool",
          "desc": "“Palestinian couscous” with chicken and chickpeas",
          "price": 40
      },
      {
          "id": 74,
          "img": "./Images/Category/OurCuisine/Schnitzel.jpg",
          "bg": "fbf0f4",
          "title": "Schnitzel",
          "desc": "Traditional chicken meat",
          "price": 35
      },
      {
          "id": 75,
          "img": "./Images/Category/OurCuisine/Shawarma_Roll.jpg",
          "bg": "fbf0f4",
          "title": "Shawarma Roll",
          "desc": "Saj Bread filled with Beaf meat",
          "price": 40
      },
      {
          "id": 76,
          "img": "./Images/Category/OurCuisine/Shish_Barak.jpg",
          "bg": "fbf0f4",
          "title": "Shish Barak",
          "desc": "These are Middle Eastern meat filled dumplings cooked in a yogurt based sauce. It is one of the top comfort foods in Arabic cuisine",
          "price": 60
      },
      {
          "id": 77,
          "img": "./Images/Category/OurCuisine/Sweet_Pumpkin.jpg",
          "bg": "fbf0f4",
          "title": "Sweet Pumpkin",
          "desc": "Pumpkin cooked and covered by Sugar&Water syrop",
          "price": 40
      }
  ]
}
